Workbook
Name aporte: 'Analise Rendimentos'!$D$14
Name patrimonio: 'Analise Rendimentos'!$D$17
Name qnt_anos: 'Analise Rendimentos'!$D$15
Name rendimento_carteira: 'Analise Rendimentos'!$D$10
Name taxa_mensal: 'Analise Rendimentos'!$D$16

Sheet Analise Rendimentos
B8: CONFIGURAÇÕES
B9: Salário | D9: 5000
B10: Rendimento Carteira | D10: 0.006
B11: Sugestão Investimento | D11: =D9*30% -> 1500
B13: INVESTIMENTO MENSAL
B14: Quanto investir por mês? | D14: 500
B15: Quantos anos tem que investir? | D15: 5
B16: Qual a taxa de rendimento mensal? | D16: 0.01079
B17: Quanto de patrimônio acumulado? | D17: =FV(taxa_mensal,qnt_anos*12,aporte*-1) -> 41888.457
B18: Quanto é os dividendos mensais? | D18: =patrimonio*rendimento_carteira -> 251.33074
B20: CENÁRIOS | D20: Dividendo
A21: 2 | B21: Quanto em 2 anos? | C21: =FV($D$16,A$21*12,D14*-1) -> 13613.814 | D21: =C21*rendimento_carteira -> 81.682882
A22: 5 | B22: Quanto em 5 anos? | C22: =FV($D$16,A$22*12,D14*-1) -> 41888.457 | D22: =C22*rendimento_carteira -> 251.33074
A23: 10 | B23: Quanto em 10 anos? | C23: =FV($D$16,A$23*12,D14*-1) -> 121642.11 | D23: =C23*rendimento_carteira -> 729.85264
A24: 20 | B24: Quanto em 20 anos? | C24: =FV($D$16,A$24*12,D14*-1) -> 562599.2 | D24: =C24*rendimento_carteira -> 3375.5952
A25: 30 | B25: Quanto em 30 anos? | C25: =FV($D$16,A$25*12,D14*-1) -> 2161084.8 | D25: =C25*rendimento_carteira -> 12966.509
B29: Perfil | C29: Moderado
B30: Valor a ser investido por mês | C30: =aporte -> 500
B32: Tipo de FII | C32: Percentual Sugerido | D32: Valores
B33: Papel | C33: =VLOOKUP($C$29&"-"&B33,Auxiliar!A:D,4,) -> 0.32 | D33: =C33*$C$30 -> 160
B34: Tijolo | C34: =VLOOKUP($C$29&"-"&B34,Auxiliar!A:D,4,) -> 0.35 | D34: =C34*$C$30 -> 175
B35: Híbridos | C35: =VLOOKUP($C$29&"-"&B35,Auxiliar!A:D,4,) -> 0.08 | D35: =C35*$C$30 -> 40
B36: FOFs | C36: =VLOOKUP($C$29&"-"&B36,Auxiliar!A:D,4,) -> 0.05 | D36: =C36*$C$30 -> 25
B37: Desenvolvimento | C37: =VLOOKUP($C$29&"-"&B37,Auxiliar!A:D,4,) -> 0.1 | D37: =C37*$C$30 -> 50
B38: Hotelarias | C38: =VLOOKUP($C$29&"-"&B38,Auxiliar!A:D,4,) -> 0.1 | D38: =C38*$C$30 -> 50
D39: =SUM(D33:D38) -> 500

Sheet Auxiliar
A2: CHAVE | B2: PERFIL | C2: TIPOS DE FII | D2: %
A3: =B3&"-"&C3 -> Conservador-Papel | B3: Conservador | C3: Papel | D3: 0.3
A4: =B4&"-"&C4 -> Conservador-Tijolo | B4: Conservador | C4: Tijolo | D4: 0.5
A5: =B5&"-"&C5 -> Conservador-Híbridos | B5: Conservador | C5: Híbridos | D5: 0.1
A6: =B6&"-"&C6 -> Conservador-FOFs | B6: Conservador | C6: FOFs | D6: 0.1
A7: =B7&"-"&C7 -> Conservador-Desenvolvimento | B7: Conservador | C7: Desenvolvimento | D7: 0
A8: =B8&"-"&C8 -> Conservador-Hotelarias | B8: Conservador | C8: Hotelarias | D8: 0
A9: =B9&"-"&C9 -> Moderado-Papel | B9: Moderado | C9: Papel | D9: 0.32
A10: =B10&"-"&C10 -> Moderado-Tijolo | B10: Moderado | C10: Tijolo | D10: 0.35
A11: =B11&"-"&C11 -> Moderado-Híbridos | B11: Moderado | C11: Híbridos | D11: 0.08
A12: =B12&"-"&C12 -> Moderado-FOFs | B12: Moderado | C12: FOFs | D12: 0.05
A13: =B13&"-"&C13 -> Moderado-Desenvolvimento | B13: Moderado | C13: Desenvolvimento | D13: 0.1
A14: =B14&"-"&C14 -> Moderado-Hotelarias | B14: Moderado | C14: Hotelarias | D14: 0.1
... A20: =B20&"-"&C20 -> Agressivo-Hotelarias | B20: Agressivo | C20: Hotelarias | D20: 0.1
